GHEtool/Borefield.py
GHEtool/__init__.py
GHEtool/Methods/__init__.py
GHEtool/Methods/optimise_borefield_configuration.py
GHEtool/Methods/optimise_load_profile.py
GHEtool/Validation/Resistances.dat
GHEtool/Validation/__init__.py
GHEtool/Validation/artificial_neural_network.py
GHEtool/Validation/cases.py
GHEtool/Validation/enhanced_sizing_method.py
GHEtool/Validation/optimise_borefield_configuration.py
GHEtool/Validation/resistances_EED.csv
GHEtool/Validation/sizing_method_comparison.py
GHEtool/Validation/sizing_method_comparison_L2_L3_L4.py
GHEtool/Validation/speed_comparison.py
GHEtool/Validation/validate_deep_sizing.py
GHEtool/Validation/validation_effective_borehole_thermal_resistance.py
GHEtool/VariableClasses/BaseClass.py
GHEtool/VariableClasses/Borehole.py
GHEtool/VariableClasses/CalculationSetup.py
GHEtool/VariableClasses/Cylindrical_correction.py
GHEtool/VariableClasses/Result.py
GHEtool/VariableClasses/__init__.py
GHEtool/VariableClasses/Efficiency/COP.py
GHEtool/VariableClasses/Efficiency/EER.py
GHEtool/VariableClasses/Efficiency/EERCombined.py
GHEtool/VariableClasses/Efficiency/SCOP.py
GHEtool/VariableClasses/Efficiency/SEER.py
GHEtool/VariableClasses/Efficiency/_Efficiency.py
GHEtool/VariableClasses/Efficiency/__init__.py
GHEtool/VariableClasses/FlowData/ConstantFlowRate.py
GHEtool/VariableClasses/FlowData/_FlowData.py
GHEtool/VariableClasses/FlowData/__init__.py
GHEtool/VariableClasses/FluidData/ConstantFluidData.py
GHEtool/VariableClasses/FluidData/TemperatureDependentFluidData.py
GHEtool/VariableClasses/FluidData/_FluidData.py
GHEtool/VariableClasses/FluidData/__init__.py
GHEtool/VariableClasses/FluidData/CommercialFluids/CoolflowNTP.py
GHEtool/VariableClasses/FluidData/CommercialFluids/KilfrostGEO.py
GHEtool/VariableClasses/FluidData/CommercialFluids/KilfrostGEOPlus.py
GHEtool/VariableClasses/FluidData/CommercialFluids/ThermoxDTX.py
GHEtool/VariableClasses/FluidData/CommercialFluids/_CommercialFluids.py
ghetool-2.4.0.dist-info/licenses/LICENSE.txt
ghetool-2.4.0.dist-info/METADATA
ghetool-2.4.0.dist-info/WHEEL
ghetool-2.4.0.dist-info/top_level.txt
ghetool-2.4.0.dist-info/RECORD
