Metadata-Version: 2.4
Name: GHEtool
Version: 2.4.0
Summary: Python package for borefield sizing
Home-page: https://ghetool.eu
Author: Wouter Peere
Author-email: wouter@ghetool.eu
Classifier: Programming Language :: Python :: 3
Classifier: License :: OSI Approved :: BSD License
Classifier: Operating System :: OS Independent
Requires-Python: >=3.9
License-File: LICENSE.txt
Requires-Dist: matplotlib>=3.9.2
Requires-Dist: numpy>=1.26.4
Requires-Dist: pandas>=1.4.3
Requires-Dist: scipy>=1.8.1
Requires-Dist: pygfunction==2.3.0
Requires-Dist: secondarycoolantprops>=1.1
Requires-Dist: optuna>=3.6.1
Dynamic: license-file
